helios_lib/__init__.py
helios_lib/config.py
helios_lib/exceptions.py
helios_lib/models.py
helios_lib/serializer.py
helios_lib/utils.py
helios_lib/crypto/__init__.py
helios_lib/crypto/algs.py
helios_lib/crypto/electionalgs.py
helios_lib/crypto/elgamal.py
helios_lib/crypto/number.py
helios_lib/crypto/numtheory.py
helios_lib/crypto/randpool.py
helios_lib/crypto/utils.py
helios_lib/tests/__init__.py
helios_lib/tests/test_election.py
helios_lib/workflows/__init__.py
helios_lib/workflows/homomorphic.py
helios_lib-0.0.1.dist-info/LICENSE
helios_lib-0.0.1.dist-info/METADATA
helios_lib-0.0.1.dist-info/WHEEL
helios_lib-0.0.1.dist-info/top_level.txt
helios_lib-0.0.1.dist-info/RECORD
