Metadata-Version: 2.1
Name: helios-lib
Version: 0.0.1
Summary: Helios Server (Helios is an end-to-end verifiable voting system) as library
Home-page: https://github.com/anarvote/helios_lib
Author: Omid Raha
Author-email: or@omidraha.com
License: UNKNOWN
Platform: UNKNOWN
Classifier: Programming Language :: Python :: 2
Classifier: License :: OSI Approved :: MIT License
Classifier: Operating System :: OS Independent
Requires-Dist: pytest (==3.6.2)
